README.rst
UNLICENSE
setup.py
doc/conf.py
doc/gettingstarted.rst
doc/index.rst
doc/modules.rst
doc/recipes.rst
doc/userguide.rst
doc/_build/.gitignore
doc/_static/.gitignore
doc/_templates/.gitignore
etc/nose.cfg
src/weblayer/__init__.py
src/weblayer/auth.py
src/weblayer/base.py
src/weblayer/bootstrap.py
src/weblayer/component.py
src/weblayer/cookie.py
src/weblayer/interfaces.py
src/weblayer/method.py
src/weblayer/normalise.py
src/weblayer/request.py
src/weblayer/route.py
src/weblayer/settings.py
src/weblayer/static.py
src/weblayer/template.py
src/weblayer/utils.py
src/weblayer/wsgi.py
src/weblayer.egg-info/PKG-INFO
src/weblayer.egg-info/SOURCES.txt
src/weblayer.egg-info/dependency_links.txt
src/weblayer.egg-info/entry_points.txt
src/weblayer.egg-info/not-zip-safe
src/weblayer.egg-info/requires.txt
src/weblayer.egg-info/top_level.txt
src/weblayer/examples/__init__.py
src/weblayer/examples/helloworld.py
src/weblayer/examples/deploy/appengine/app.py
src/weblayer/examples/deploy/appengine/app.yaml
src/weblayer/examples/deploy/mod_wsgi/app.wsgi
src/weblayer/examples/deploy/paste/config.ini
src/weblayer/examples/deploy/paste/demo.py
src/weblayer/examples/deploy/paste/setup.py
src/weblayer/examples/override/authentication_manager.py
src/weblayer/examples/override/path_router.py
src/weblayer/examples/override/template_renderer.py
src/weblayer/tests/__init__.py
src/weblayer/tests/test_bootstrap.py
src/weblayer/tests/test_cookie.py
src/weblayer/tests/test_method.py
src/weblayer/tests/test_request.py
src/weblayer/tests/test_settings.py
src/weblayer/tests/test_template.py
src/weblayer/tests/test_wsgi.py
src/weblayer/tests/fixtures/__init__.py
src/weblayer/tests/fixtures/double_import.py
src/weblayer/tests/fixtures/double_import_single_require.py
src/weblayer/tests/fixtures/override.py
src/weblayer/tests/fixtures/require.py
src/weblayer/tests/fixtures/single_require.py
src/weblayer/tests/ftests/__init__.py
src/weblayer/tests/ftests/test_api.py
src/weblayer/tests/ftests/test_hello_world.py
src/weblayer/tests/ftests/static/foo.js
src/weblayer/tests/ftests/templates/builtins.tmpl
src/weblayer/tests/ftests/templates/request.tmpl